{
    "data": [
        {
            "assists": 36,
            "evGoals": 10,
            "evPoints": 31,
            "faceoffWinPct": null,
            "gameWinningGoals": 3,
            "gamesPlayed": 45,
            "goals": 15,
            "lastName": "Werenski",
            "otGoals": 1,
            "penaltyMinutes": 25,
            "playerId": 8478460,
            "plusMinus": 11,
            "points": 51,
            "pointsPerGame": 1.13333,
            "positionCode": "D",
            "ppGoals": 5,
            "ppPoints": 19,
            "shGoals": 0,
            "shPoints": 1,
            "shootingPct": 0.08426,
            "shootsCatches": "L",
            "shots": 178,
            "skaterFullName": "Zach Werenski",
            "timeOnIcePerGame": 1601.0
        },
        {
            "assists": 31,
            "evGoals": 16,
            "evPoints": 34,
            "faceoffWinPct": 0.32352,
            "gameWinningGoals": 1,
            "gamesPlayed": 45,
            "goals": 18,
            "lastName": "Marchenko",
            "otGoals": 0,
            "penaltyMinutes": 12,
            "playerId": 8480893,
            "plusMinus": 28,
            "points": 49,
            "pointsPerGame": 1.08888,
            "positionCode": "R",
            "ppGoals": 2,
            "ppPoints": 15,
            "shGoals": 0,
            "shPoints": 0,
            "shootingPct": 0.13636,
            "shootsCatches": "R",
            "shots": 132,
            "skaterFullName": "Kirill Marchenko",
            "timeOnIcePerGame": 1119.8888
        },
        {
            "assists": 27,
            "evGoals": 10,
            "evPoints": 30,
            "faceoffWinPct": 0.51467,
            "gameWinningGoals": 2,
            "gamesPlayed": 41,
            "goals": 14,
            "lastName": "Monahan",
            "otGoals": 0,
            "penaltyMinutes": 14,
            "playerId": 8477497,
            "plusMinus": 17,
            "points": 41,
            "pointsPerGame": 1.0,
            "positionCode": "C",
            "ppGoals": 4,
            "ppPoints": 9,
            "shGoals": 0,
            "shPoints": 2,
            "shootingPct": 0.13207,
            "shootsCatches": "L",
            "shots": 106,
            "skaterFullName": "Sean Monahan",
            "timeOnIcePerGame": 1166.7804
        },
        {
            "assists": 13,
            "evGoals": 10,
            "evPoints": 22,
            "faceoffWinPct": 0.48648,
            "gameWinningGoals": 1,
            "gamesPlayed": 36,
            "goals": 17,
            "lastName": "Voronkov",
            "otGoals": 0,
            "penaltyMinutes": 37,
            "playerId": 8481716,
            "plusMinus": 16,
            "points": 30,
            "pointsPerGame": 0.83333,
            "positionCode": "L",
            "ppGoals": 7,
            "ppPoints": 8,
            "shGoals": 0,
            "shPoints": 0,
            "shootingPct": 0.21794,
            "shootsCatches": "L",
            "shots": 78,
            "skaterFullName": "Dmitri Voronkov",
            "timeOnIcePerGame": 1019.2777
        },
        {
            "assists": 14,
            "evGoals": 10,
            "evPoints": 15,
            "faceoffWinPct": 0.0,
            "gameWinningGoals": 2,
            "gamesPlayed": 31,
            "goals": 12,
            "lastName": "Johnson",
            "otGoals": 0,
            "penaltyMinutes": 8,
            "playerId": 8482660,
            "plusMinus": -5,
            "points": 26,
            "pointsPerGame": 0.8387,
            "positionCode": "C",
            "ppGoals": 1,
            "ppPoints": 9,
            "shGoals": 1,
            "shPoints": 2,
            "shootingPct": 0.19672,
            "shootsCatches": "L",
            "shots": 61,
            "skaterFullName": "Kent Johnson",
            "timeOnIcePerGame": 1041.7096
        },
        {
            "assists": 16,
            "evGoals": 4,
            "evPoints": 18,
            "faceoffWinPct": 0.49227,
            "gameWinningGoals": 1,
            "gamesPlayed": 43,
            "goals": 7,
            "lastName": "Sillinger",
            "otGoals": 0,
            "penaltyMinutes": 31,
            "playerId": 8482705,
            "plusMinus": -14,
            "points": 23,
            "pointsPerGame": 0.53488,
            "positionCode": "C",
            "ppGoals": 2,
            "ppPoints": 3,
            "shGoals": 1,
            "shPoints": 2,
            "shootingPct": 0.06862,
            "shootsCatches": "L",
            "shots": 102,
            "skaterFullName": "Cole Sillinger",
            "timeOnIcePerGame": 1055.6046
        },
        {
            "assists": 12,
            "evGoals": 9,
            "evPoints": 19,
            "faceoffWinPct": 0.41666,
            "gameWinningGoals": 1,
            "gamesPlayed": 45,
            "goals": 11,
            "lastName": "Fantilli",
            "otGoals": 0,
            "penaltyMinutes": 10,
            "playerId": 8484166,
            "plusMinus": -6,
            "points": 23,
            "pointsPerGame": 0.51111,
            "positionCode": "C",
            "ppGoals": 2,
            "ppPoints": 4,
            "shGoals": 0,
            "shPoints": 0,
            "shootingPct": 0.12359,
            "shootsCatches": "L",
            "shots": 89,
            "skaterFullName": "Adam Fantilli",
            "timeOnIcePerGame": 997.3777
        },
        {
            "assists": 13,
            "evGoals": 6,
            "evPoints": 19,
            "faceoffWinPct": null,
            "gameWinningGoals": 1,
            "gamesPlayed": 42,
            "goals": 6,
            "lastName": "Severson",
            "otGoals": 0,
            "penaltyMinutes": 14,
            "playerId": 8476923,
            "plusMinus": 3,
            "points": 19,
            "pointsPerGame": 0.45238,
            "positionCode": "D",
            "ppGoals": 0,
            "ppPoints": 0,
            "shGoals": 0,
            "shPoints": 0,
            "shootingPct": 0.08823,
            "shootsCatches": "R",
            "shots": 68,
            "skaterFullName": "Damon Severson",
            "timeOnIcePerGame": 1255.6428
        },
        {
            "assists": 16,
            "evGoals": 2,
            "evPoints": 15,
            "faceoffWinPct": null,
            "gameWinningGoals": 0,
            "gamesPlayed": 45,
            "goals": 3,
            "lastName": "Provorov",
            "otGoals": 0,
            "penaltyMinutes": 14,
            "playerId": 8478500,
            "plusMinus": 2,
            "points": 19,
            "pointsPerGame": 0.42222,
            "positionCode": "D",
            "ppGoals": 1,
            "ppPoints": 3,
            "shGoals": 0,
            "shPoints": 1,
            "shootingPct": 0.05769,
            "shootsCatches": "L",
            "shots": 52,
            "skaterFullName": "Ivan Provorov",
            "timeOnIcePerGame": 1404.0
        },
        {
            "assists": 9,
            "evGoals": 7,
            "evPoints": 15,
            "faceoffWinPct": 0.18181,
            "gameWinningGoals": 0,
            "gamesPlayed": 38,
            "goals": 8,
            "lastName": "van Riemsdyk",
            "otGoals": 0,
            "penaltyMinutes": 8,
            "playerId": 8474037,
            "plusMinus": -6,
            "points": 17,
            "pointsPerGame": 0.44736,
            "positionCode": "L",
            "ppGoals": 1,
            "ppPoints": 2,
            "shGoals": 0,
            "shPoints": 0,
            "shootingPct": 0.19047,
            "shootsCatches": "L",
            "shots": 42,
            "skaterFullName": "James van Riemsdyk",
            "timeOnIcePerGame": 741.4473
        },
        {
            "assists": 7,
            "evGoals": 9,
            "evPoints": 16,
            "faceoffWinPct": 0.375,
            "gameWinningGoals": 3,
            "gamesPlayed": 45,
            "goals": 10,
            "lastName": "Olivier",
            "otGoals": 0,
            "penaltyMinutes": 83,
            "playerId": 8479671,
            "plusMinus": -7,
            "points": 17,
            "pointsPerGame": 0.37777,
            "positionCode": "R",
            "ppGoals": 0,
            "ppPoints": 0,
            "shGoals": 1,
            "shPoints": 1,
            "shootingPct": 0.18518,
            "shootsCatches": "R",
            "shots": 54,
            "skaterFullName": "Mathieu Olivier",
            "timeOnIcePerGame": 851.2666
        },
        {
            "assists": 7,
            "evGoals": 5,
            "evPoints": 9,
            "faceoffWinPct": null,
            "gameWinningGoals": 1,
            "gamesPlayed": 21,
            "goals": 7,
            "lastName": "Chinakhov",
            "otGoals": 0,
            "penaltyMinutes": 2,
            "playerId": 8482475,
            "plusMinus": 2,
            "points": 14,
            "pointsPerGame": 0.66666,
            "positionCode": "R",
            "ppGoals": 2,
            "ppPoints": 5,
            "shGoals": 0,
            "shPoints": 0,
            "shootingPct": 0.12727,
            "shootsCatches": "L",
            "shots": 55,
            "skaterFullName": "Yegor Chinakhov",
            "timeOnIcePerGame": 1021.238
        },
        {
            "assists": 10,
            "evGoals": 2,
            "evPoints": 12,
            "faceoffWinPct": 0.0,
            "gameWinningGoals": 0,
            "gamesPlayed": 32,
            "goals": 2,
            "lastName": "Labanc",
            "otGoals": 0,
            "penaltyMinutes": 12,
            "playerId": 8478099,
            "plusMinus": 2,
            "points": 12,
            "pointsPerGame": 0.375,
            "positionCode": "R",
            "ppGoals": 0,
            "ppPoints": 0,
            "shGoals": 0,
            "shPoints": 0,
            "shootingPct": 0.0606,
            "shootsCatches": "R",
            "shots": 33,
            "skaterFullName": "Kevin Labanc",
            "timeOnIcePerGame": 631.9375
        },
        {
            "assists": 7,
            "evGoals": 4,
            "evPoints": 11,
            "faceoffWinPct": 0.28571,
            "gameWinningGoals": 1,
            "gamesPlayed": 44,
            "goals": 4,
            "lastName": "Aston-Reese",
            "otGoals": 0,
            "penaltyMinutes": 21,
            "playerId": 8479944,
            "plusMinus": -8,
            "points": 11,
            "pointsPerGame": 0.25,
            "positionCode": "C",
            "ppGoals": 0,
            "ppPoints": 0,
            "shGoals": 0,
            "shPoints": 0,
            "shootingPct": 0.07142,
            "shootsCatches": "L",
            "shots": 56,
            "skaterFullName": "Zach Aston-Reese",
            "timeOnIcePerGame": 796.5454
        },
        {
            "assists": 7,
            "evGoals": 4,
            "evPoints": 11,
            "faceoffWinPct": 0.52805,
            "gameWinningGoals": 0,
            "gamesPlayed": 45,
            "goals": 4,
            "lastName": "Kuraly",
            "otGoals": 0,
            "penaltyMinutes": 16,
            "playerId": 8476374,
            "plusMinus": 0,
            "points": 11,
            "pointsPerGame": 0.24444,
            "positionCode": "C",
            "ppGoals": 0,
            "ppPoints": 0,
            "shGoals": 0,
            "shPoints": 0,
            "shootingPct": 0.10256,
            "shootsCatches": "L",
            "shots": 39,
            "skaterFullName": "Sean Kuraly",
            "timeOnIcePerGame": 674.5333
        },
        {
            "assists": 7,
            "evGoals": 3,
            "evPoints": 10,
            "faceoffWinPct": null,
            "gameWinningGoals": 1,
            "gamesPlayed": 29,
            "goals": 3,
            "lastName": "Fabbro",
            "otGoals": 0,
            "penaltyMinutes": 22,
            "playerId": 8479371,
            "plusMinus": 14,
            "points": 10,
            "pointsPerGame": 0.34482,
            "positionCode": "D",
            "ppGoals": 0,
            "ppPoints": 0,
            "shGoals": 0,
            "shPoints": 0,
            "shootingPct": 0.08108,
            "shootsCatches": "R",
            "shots": 37,
            "skaterFullName": "Dante Fabbro",
            "timeOnIcePerGame": 1308.3448
        },
        {
            "assists": 5,
            "evGoals": 2,
            "evPoints": 6,
            "faceoffWinPct": 0.48214,
            "gameWinningGoals": 0,
            "gamesPlayed": 25,
            "goals": 3,
            "lastName": "Danforth",
            "otGoals": 0,
            "penaltyMinutes": 8,
            "playerId": 8479941,
            "plusMinus": -7,
            "points": 8,
            "pointsPerGame": 0.32,
            "positionCode": "R",
            "ppGoals": 0,
            "ppPoints": 1,
            "shGoals": 1,
            "shPoints": 1,
            "shootingPct": 0.06122,
            "shootsCatches": "R",
            "shots": 49,
            "skaterFullName": "Justin Danforth",
            "timeOnIcePerGame": 920.44
        },
        {
            "assists": 6,
            "evGoals": 1,
            "evPoints": 7,
            "faceoffWinPct": null,
            "gameWinningGoals": 0,
            "gamesPlayed": 45,
            "goals": 1,
            "lastName": "Christiansen",
            "otGoals": 0,
            "penaltyMinutes": 11,
            "playerId": 8481161,
            "plusMinus": 4,
            "points": 7,
            "pointsPerGame": 0.15555,
            "positionCode": "D",
            "ppGoals": 0,
            "ppPoints": 0,
            "shGoals": 0,
            "shPoints": 0,
            "shootingPct": 0.02083,
            "shootsCatches": "L",
            "shots": 48,
            "skaterFullName": "Jake Christiansen",
            "timeOnIcePerGame": 787.0444
        },
        {
            "assists": 2,
            "evGoals": 3,
            "evPoints": 5,
            "faceoffWinPct": 0.5,
            "gameWinningGoals": 0,
            "gamesPlayed": 35,
            "goals": 4,
            "lastName": "Pyyhtia",
            "otGoals": 0,
            "penaltyMinutes": 6,
            "playerId": 8482451,
            "plusMinus": -9,
            "points": 6,
            "pointsPerGame": 0.17142,
            "positionCode": "L",
            "ppGoals": 0,
            "ppPoints": 0,
            "shGoals": 1,
            "shPoints": 1,
            "shootingPct": 0.14814,
            "shootsCatches": "L",
            "shots": 27,
            "skaterFullName": "Mikael Pyyhtia",
            "timeOnIcePerGame": 741.6
        },
        {
            "assists": 2,
            "evGoals": 1,
            "evPoints": 2,
            "faceoffWinPct": 0.38636,
            "gameWinningGoals": 0,
            "gamesPlayed": 4,
            "goals": 1,
            "lastName": "Del Bel Belluz",
            "otGoals": 0,
            "penaltyMinutes": 0,
            "playerId": 8483432,
            "plusMinus": 2,
            "points": 3,
            "pointsPerGame": 0.75,
            "positionCode": "C",
            "ppGoals": 0,
            "ppPoints": 1,
            "shGoals": 0,
            "shPoints": 0,
            "shootingPct": 0.33333,
            "shootsCatches": "L",
            "shots": 3,
            "skaterFullName": "Luca Del Bel Belluz",
            "timeOnIcePerGame": 778.75
        },
        {
            "assists": 2,
            "evGoals": 1,
            "evPoints": 3,
            "faceoffWinPct": null,
            "gameWinningGoals": 0,
            "gamesPlayed": 11,
            "goals": 1,
            "lastName": "Mateychuk",
            "otGoals": 0,
            "penaltyMinutes": 2,
            "playerId": 8483485,
            "plusMinus": -2,
            "points": 3,
            "pointsPerGame": 0.27272,
            "positionCode": "D",
            "ppGoals": 0,
            "ppPoints": 0,
            "shGoals": 0,
            "shPoints": 0,
            "shootingPct": 0.0909,
            "shootsCatches": "L",
            "shots": 11,
            "skaterFullName": "Denton Mateychuk",
            "timeOnIcePerGame": 1075.7272
        },
        {
            "assists": 2,
            "evGoals": 1,
            "evPoints": 3,
            "faceoffWinPct": null,
            "gameWinningGoals": 0,
            "gamesPlayed": 24,
            "goals": 1,
            "lastName": "Harris",
            "otGoals": 0,
            "penaltyMinutes": 6,
            "playerId": 8480887,
            "plusMinus": -5,
            "points": 3,
            "pointsPerGame": 0.125,
            "positionCode": "D",
            "ppGoals": 0,
            "ppPoints": 0,
            "shGoals": 0,
            "shPoints": 0,
            "shootingPct": 0.08333,
            "shootsCatches": "L",
            "shots": 12,
            "skaterFullName": "Jordan Harris",
            "timeOnIcePerGame": 699.0833
        },
        {
            "assists": 2,
            "evGoals": 0,
            "evPoints": 2,
            "faceoffWinPct": null,
            "gameWinningGoals": 0,
            "gamesPlayed": 27,
            "goals": 0,
            "lastName": "Johnson",
            "otGoals": 0,
            "penaltyMinutes": 2,
            "playerId": 8471677,
            "plusMinus": -7,
            "points": 2,
            "pointsPerGame": 0.07407,
            "positionCode": "D",
            "ppGoals": 0,
            "ppPoints": 0,
            "shGoals": 0,
            "shPoints": 0,
            "shootingPct": 0.0,
            "shootsCatches": "L",
            "shots": 14,
            "skaterFullName": "Jack Johnson",
            "timeOnIcePerGame": 775.8888
        },
        {
            "assists": 1,
            "evGoals": 0,
            "evPoints": 1,
            "faceoffWinPct": null,
            "gameWinningGoals": 0,
            "gamesPlayed": 6,
            "goals": 0,
            "lastName": "Jiricek",
            "otGoals": 0,
            "penaltyMinutes": 4,
            "playerId": 8483460,
            "plusMinus": -2,
            "points": 1,
            "pointsPerGame": 0.16666,
            "positionCode": "D",
            "ppGoals": 0,
            "ppPoints": 0,
            "shGoals": 0,
            "shPoints": 0,
            "shootingPct": 0.0,
            "shootsCatches": "R",
            "shots": 5,
            "skaterFullName": "David Jiricek",
            "timeOnIcePerGame": 671.8333
        },
        {
            "assists": 0,
            "evGoals": 0,
            "evPoints": 0,
            "faceoffWinPct": 0.4,
            "gameWinningGoals": 0,
            "gamesPlayed": 1,
            "goals": 0,
            "lastName": "Sillinger",
            "otGoals": 0,
            "penaltyMinutes": 2,
            "playerId": 8483538,
            "plusMinus": 0,
            "points": 0,
            "pointsPerGame": 0.0,
            "positionCode": "C",
            "ppGoals": 0,
            "ppPoints": 0,
            "shGoals": 0,
            "shPoints": 0,
            "shootingPct": null,
            "shootsCatches": "L",
            "shots": 0,
            "skaterFullName": "Owen Sillinger",
            "timeOnIcePerGame": 789.0
        }
    ],
    "total": 27
}